hypothesis_geometry/__init__.py
hypothesis_geometry/hints.py
hypothesis_geometry/planar.py
hypothesis_geometry/py.typed
hypothesis_geometry/_core/__init__.py
hypothesis_geometry/_core/base.py
hypothesis_geometry/_core/constants.py
hypothesis_geometry/_core/contracts.py
hypothesis_geometry/_core/factories.py
hypothesis_geometry/_core/hints.py
hypothesis_geometry/_core/subdivisional.py
hypothesis_geometry/_core/triangular.py
hypothesis_geometry/_core/utils.py
hypothesis_geometry-9.0.0.dist-info/licenses/LICENSE
hypothesis_geometry-9.0.0.dist-info/METADATA
hypothesis_geometry-9.0.0.dist-info/WHEEL
hypothesis_geometry-9.0.0.dist-info/top_level.txt
hypothesis_geometry-9.0.0.dist-info/RECORD
