Metadata-Version: 2.4
Name: hypothesis_geometry
Version: 9.0.0
Summary: ``hypothesis`` strategies for geometries.
Home-page: https://github.com/lycantropos/hypothesis_geometry/
Download-URL: https://github.com/lycantropos/hypothesis_geometry/archive/master.zip
Author-email: Azat Ibrakov <azatibrakov@gmail.com>
License: MIT License
Classifier: License :: OSI Approved :: MIT License
Classifier: Programming Language :: Python :: 3.10
Classifier: Programming Language :: Python :: 3.11
Classifier: Programming Language :: Python :: 3.12
Classifier: Programming Language :: Python :: 3.13
Classifier: Programming Language :: Python :: 3.14
Classifier: Programming Language :: Python :: Implementation :: CPython
Classifier: Programming Language :: Python :: Implementation :: PyPy
Requires-Python: >=3.10
License-File: LICENSE
Requires-Dist: bentley-ottmann<10.0,>=9.0.1
Requires-Dist: decision<1.0,>=0.4.0
Requires-Dist: dendroid<3.0,>=2.1.0
Requires-Dist: ground<13.0,>=12.0.0
Requires-Dist: hypothesis<7.0,>=6.150.2
Requires-Dist: locus<12.0,>=11.0.0
Requires-Dist: reprit<1.0,>=0.9.0
Provides-Extra: docs
Requires-Dist: Sphinx<9.0,>=7.2.6; extra == "docs"
Requires-Dist: sphinx-rtd-theme<3.0,>=2.0.0; extra == "docs"
Provides-Extra: tests
Requires-Dist: pytest<10.0,>=9.0.2; extra == "tests"
Dynamic: download-url
Dynamic: home-page
Dynamic: license-file
